djohno-0.2.0.dist-info/DESCRIPTION.rst
djohno-0.2.0.dist-info/pydist.json
djohno-0.2.0.dist-info/top_level.txt
djohno-0.2.0.dist-info/RECORD
djohno-0.2.0.dist-info/WHEEL
djohno-0.2.0.dist-info/METADATA
djohno/utils.py
djohno/urls.py
djohno/models.py
djohno/views.py
djohno/__init__.py
djohno/static/djohno/djohno_pages.css
djohno/static/djohno/djohno.ico
djohno/static/djohno/style.css
djohno/templates/500.html
djohno/templates/404.html
djohno/templates/403.html
djohno/templates/djohno/_djohno_dose.html
djohno/templates/djohno/base.html
djohno/templates/djohno/index.html
djohno/templates/djohno/frame.html
djohno/templates/djohno/_bad_email_invalid.html
djohno/templates/djohno/email.html
djohno/templates/djohno/bad_email.html
djohno/templates/djohno/_bad_email_default.html
djohno/templates/djohno/email_sent.html
djohno/templates/djohno/email_body.txt
tests/test_mail_views.py
tests/test_views.py
tests/utils.py
tests/test_utils.py
tests/urls.py
tests/test_view_permissions.py
tests/settings.py
tests/__init__.py
tests/baz/models.py
tests/baz/__init__.py
tests/moo/models.py
tests/moo/__init__.py
