Metadata-Version: 2.0
Name: djohno
Version: 0.2.0
Summary: A tiny Django app for checking over your error pages.
Home-page: https://github.com/dominicrodger/djohno
Author: Dominic Rodger
Author-email: internet@dominicrodger.com
License: BSD
Platform: UNKNOWN
Classifier: Development Status :: 5 - Production/Stable
Classifier: Environment :: Web Environment
Classifier: Framework :: Django
Classifier: Intended Audience :: Developers
Classifier: License :: OSI Approved :: BSD License
Classifier: Operating System :: OS Independent
Classifier: Programming Language :: Python :: 2.6
Classifier: Programming Language :: Python :: 2.7
Classifier: Programming Language :: Python :: 3.3
Requires-Dist: Django (>=1.4)
